{"bar": [{"category": "半導體業", "category_en": "Semiconductor", "thisYear": 1422.5, "market": "上市", "market_en": "Listed"}, {"category": "金融保險業", "category_en": "Finance & Insurance", "thisYear": 1272.6, "market": "上市", "market_en": "Listed"}, {"category": "半導體業", "category_en": "Semiconductor", "thisYear": 1180.2, "market": "上櫃", "market_en": "OTC"}, {"category": "電子通路業", "category_en": "Electronics Distributor", "thisYear": 1153.6, "market": "上市", "market_en": "Listed"}, {"category": "航運業", "category_en": "Transportation", "thisYear": 1116.9, "market": "上市", "market_en": "Listed"}, {"category": "航運業", "category_en": "Transportation", "thisYear": 1104.8, "market": "上櫃", "market_en": "OTC"}, {"category": "電腦及週邊設備業", "category_en": "Computers & Peripheral", "thisYear": 1082.3, "market": "上市", "market_en": "Listed"}, {"category": "數位雲端", "category_en": "Cloud Computing", "thisYear": 1062.7, "market": "上市", "market_en": "Listed"}, {"category": "油電燃氣業", "category_en": "Oil, Gas & Electricity", "thisYear": 1061.8, "market": "上市", "market_en": "Listed"}, {"category": "資訊服務業", "category_en": "Information Services", "thisYear": 1052.9, "market": "上市", "market_en": "Listed"}, {"category": "其他電子業", "category_en": "Other Electronic", "thisYear": 1022.2, "market": "上市", "market_en": "Listed"}, {"category": "建材營造", "category_en": "Construction", "thisYear": 1012.4, "market": "上市", "market_en": "Listed"}, {"category": "通信網路業", "category_en": "Telecommunication", "thisYear": 981.2, "market": "上市", "market_en": "Listed"}, {"category": "建材營造", "category_en": "Construction", "thisYear": 967.8, "market": "上櫃", "market_en": "OTC"}, {"category": "金融業", "category_en": "Finance & Banking", "thisYear": 936.6, "market": "上櫃", "market_en": "OTC"}, {"category": "塑膠工業", "category_en": "Plastics", "thisYear": 926.1, "market": "上市", "market_en": "Listed"}, {"category": "資訊服務業", "category_en": "Information Services", "thisYear": 913.3, "market": "上櫃", "market_en": "OTC"}, {"category": "電子零組件業", "category_en": "Electronic Parts & Components", "thisYear": 913.2, "market": "上市", "market_en": "Listed"}, {"category": "綠能環保", "category_en": "Green Energy & Environmental Tech", "thisYear": 875.1, "market": "上市", "market_en": "Listed"}, {"category": "電腦及週邊設備業", "category_en": "Computers & Peripheral", "thisYear": 855.4, "market": "上櫃", "market_en": "OTC"}, {"category": "數位雲端", "category_en": "Cloud Computing", "thisYear": 853.4, "market": "上櫃", "market_en": "OTC"}, {"category": "其他電子業", "category_en": "Other Electronic", "thisYear": 852.2, "market": "上櫃", "market_en": "OTC"}, {"category": "化學工業", "category_en": "Chemical", "thisYear": 849.4, "market": "上市", "market_en": "Listed"}, {"category": "汽車工業", "category_en": "Automobile", "thisYear": 846.1, "market": "上市", "market_en": "Listed"}, {"category": "油電燃氣業", "category_en": "Oil, Gas & Electricity", "thisYear": 846.0, "market": "上櫃", "market_en": "OTC"}, {"category": "居家生活", "category_en": "Home & Living", "thisYear": 843.6, "market": "上市", "market_en": "Listed"}, {"category": "電子通路業", "category_en": "Electronics Distributor", "thisYear": 840.1, "market": "上櫃", "market_en": "OTC"}, {"category": "通信網路業", "category_en": "Telecommunication", "thisYear": 832.4, "market": "上櫃", "market_en": "OTC"}, {"category": "生技醫療業", "category_en": "Biotech & Healthcare", "thisYear": 830.5, "market": "上櫃", "market_en": "OTC"}, {"category": "水泥工業", "category_en": "Cement Manufacturing", "thisYear": 828.4, "market": "上市", "market_en": "Listed"}, {"category": "生技醫療業", "category_en": "Biotech & Healthcare", "thisYear": 824.4, "market": "上市", "market_en": "Listed"}, {"category": "其他", "category_en": "Others", "thisYear": 806.9, "market": "上市", "market_en": "Listed"}, {"category": "光電業", "category_en": "Optoelectronic", "thisYear": 802.7, "market": "上市", "market_en": "Listed"}, {"category": "文化創意業", "category_en": "Culture & Creative", "thisYear": 798.6, "market": "上櫃", "market_en": "OTC"}, {"category": "運動休閒", "category_en": "Sports & Leisure", "thisYear": 785.5, "market": "上市", "market_en": "Listed"}, {"category": "橡膠工業", "category_en": "Rubber", "thisYear": 778.0, "market": "上市", "market_en": "Listed"}, {"category": "食品工業", "category_en": "Food Services", "thisYear": 774.7, "market": "上市", "market_en": "Listed"}, {"category": "電器電纜", "category_en": "Electrical & Cable", "thisYear": 772.9, "market": "上市", "market_en": "Listed"}, {"category": "綠能環保", "category_en": "Green Energy & Environmental Tech", "thisYear": 771.1, "market": "上櫃", "market_en": "OTC"}, {"category": "食品工業", "category_en": "Food Services", "thisYear": 764.4, "market": "上櫃", "market_en": "OTC"}, {"category": "鋼鐵工業", "category_en": "Iron & Steel", "thisYear": 762.1, "market": "上市", "market_en": "Listed"}, {"category": "電子零組件業", "category_en": "Electronic Parts & Components", "thisYear": 759.3, "market": "上櫃", "market_en": "OTC"}, {"category": "造紙工業", "category_en": "Paper Manufacturing", "thisYear": 751.0, "market": "上市", "market_en": "Listed"}, {"category": "光電業", "category_en": "Optoelectronic", "thisYear": 736.2, "market": "上櫃", "market_en": "OTC"}, {"category": "貿易百貨", "category_en": "Trade & Consumer Goods", "thisYear": 726.1, "market": "上市", "market_en": "Listed"}, {"category": "電機機械", "category_en": "Electric Machinery", "thisYear": 713.9, "market": "上市", "market_en": "Listed"}, {"category": "居家生活", "category_en": "Home & Living", "thisYear": 710.9, "market": "上櫃", "market_en": "OTC"}, {"category": "鋼鐵工業", "category_en": "Iron & Steel", "thisYear": 697.4, "market": "上櫃", "market_en": "OTC"}, {"category": "化學工業", "category_en": "Chemical", "thisYear": 696.4, "market": "上櫃", "market_en": "OTC"}, {"category": "電機機械", "category_en": "Electric Machinery", "thisYear": 673.2, "market": "上櫃", "market_en": "OTC"}, {"category": "玻璃陶瓷", "category_en": "Glass & Ceramics", "thisYear": 669.8, "market": "上市", "market_en": "Listed"}, {"category": "其他", "category_en": "Others", "thisYear": 669.3, "market": "上櫃", "market_en": "OTC"}, {"category": "紡織纖維", "category_en": "Textiles", "thisYear": 660.7, "market": "上櫃", "market_en": "OTC"}, {"category": "紡織纖維", "category_en": "Textiles", "thisYear": 640.7, "market": "上市", "market_en": "Listed"}, {"category": "觀光餐旅", "category_en": "Accommodation & Food Services", "thisYear": 633.8, "market": "上市", "market_en": "Listed"}, {"category": "農業科技", "category_en": 0, "thisYear": 616.8, "market": "上櫃", "market_en": "OTC"}, {"category": "觀光餐旅", "category_en": "Accommodation & Food Services", "thisYear": 570.2, "market": "上櫃", "market_en": "OTC"}, {"category": "運動休閒", "category_en": "Sports & Leisure", "thisYear": 569.9, "market": "上櫃", "market_en": "OTC"}, {"category": "塑膠工業", "category_en": "Plastics", "thisYear": 541.8, "market": "上櫃", "market_en": "OTC"}, {"category": "電器電纜", "category_en": "Electrical & Cable", "thisYear": 416.0, "market": "上櫃", "market_en": "OTC"}], "plot": [{"company": "中化", "company_en": "China Chemical & Pharmaceutical Co., Ltd. ", "category": "藥品製造/新藥研發", "category_en": "Bio-Pharmaceuticals", "market": "上市", "market_en": "Listed", "EPS": -0.53, "growth": -5.27}, {"company": "葡萄王", "company_en": "Grape King Bio Ltd ", "category": "食品生技及預防保健品", "category_en": "Food Science & Health Supplement", "market": "上市", "market_en": "Listed", "EPS": -0.0299999999999993, "growth": -2.2}, {"company": "生達", "company_en": "Standard Chemical & Pharmaceutical Co. Ltd. ", "category": "藥品製造/新藥研發", "category_en": "Bio-Pharmaceuticals", "market": "上市", "market_en": "Listed", "EPS": 0.1100000000000003, "growth": 7.59}, {"company": "美吾華", "company_en": "Maywufa Company Ltd. ", "category": "醫療通路/產品經銷", "category_en": "Pharmacy & Distributor", "market": "上市", "market_en": "Listed", "EPS": 0.05, "growth": 8.58}, {"company": "五鼎", "company_en": "Apex Biotechnology Corp. ", "category": "醫材製造/研發", "category_en": "Medical Device R&D, Manufacturing", "market": "上市", "market_en": "Listed", "EPS": -0.6600000000000001, "growth": -9.83}, {"company": "杏輝", "company_en": "Sinphar Pharmaceutical Co.,Ltd. ", "category": "藥品製造/新藥研發", "category_en": "Bio-Pharmaceuticals", "market": "上市", "market_en": "Listed", "EPS": 0.9000000000000001, "growth": 3.73}, {"company": "南光", "company_en": "Nang Kuang Pharmaceutical Co., Ltd. ", "category": "藥品製造/新藥研發", "category_en": "Bio-Pharmaceuticals", "market": "上市", "market_en": "Listed", "EPS": -1.5300000000000002, "growth": 2.48}, {"company": "寶齡富錦", "company_en": "Panion & Bf Biotech Inc. ", "category": "藥品製造/新藥研發", "category_en": "Bio-Pharmaceuticals", "market": "上市", "market_en": "Listed", "EPS": -1.23, "growth": -11.46}, {"company": "中化生", "company_en": "Chunghwa Chemical Synthesis & Biotech Co., Ltd. ", "category": "原料藥", "category_en": "APIs", "market": "上市", "market_en": "Listed", "EPS": -2.59, "growth": -10.96}, {"company": "和康生", "company_en": "Maxigen Biotech Inc. ", "category": "醫材製造/研發", "category_en": "Medical Device R&D, Manufacturing", "market": "上市", "market_en": "Listed", "EPS": 0.2100000000000002, "growth": 14.33}, {"company": "科妍", "company_en": "SciVision Biotech Inc. ", "category": "醫材製造/研發", "category_en": "Medical Device R&D, Manufacturing", "market": "上市", "market_en": "Listed", "EPS": 0.52, "growth": 8.5}, {"company": "神隆", "company_en": "ScinoPharm Taiwan, Ltd. ", "category": "原料藥", "category_en": "APIs", "market": "上市", "market_en": "Listed", "EPS": -0.09, "growth": 4.92}, {"company": "美時", "company_en": "Lotus Pharmaceutical Co., Ltd. ", "category": "藥品製造/新藥研發", "category_en": "Bio-Pharmaceuticals", "market": "上市", "market_en": "Listed", "EPS": 4.130000000000001, "growth": 4.29}, {"company": "景岳", "company_en": "GenMont Biotech Incorporation ", "category": "食品生技及預防保健品", "category_en": "Food Science & Health Supplement", "market": "上市", "market_en": "Listed", "EPS": -0.28, "growth": 1.19}, {"company": "永信", "company_en": "YungShin Global Holding Corporation ", "category": "藥品製造/新藥研發", "category_en": "Bio-Pharmaceuticals", "market": "上市", "market_en": "Listed", "EPS": -0.04, "growth": 8.54}, {"company": "佳醫", "company_en": "Excelsior Medical Co., Ltd. ", "category": "醫療通路/產品經銷", "category_en": "Pharmacy & Distributor", "market": "上市", "market_en": "Listed", "EPS": 0.2999999999999998, "growth": 5.31}, {"company": "雃博", "company_en": "Wellell Inc. ", "category": "醫材製造/研發", "category_en": "Medical Device R&D, Manufacturing", "market": "上市", "market_en": "Listed", "EPS": -0.09, "growth": 1.51}, {"company": "懷特", "company_en": "PhytoHealth Corporation ", "category": "藥品製造/新藥研發", "category_en": "Bio-Pharmaceuticals", "market": "上市", "market_en": "Listed", "EPS": 0.16, "growth": -8.28}, {"company": "旭富", "company_en": "SCI Pharmtech, Inc. ", "category": "原料藥", "category_en": "APIs", "market": "上市", "market_en": "Listed", "EPS": -0.54, "growth": 1.07}, {"company": "亞諾法", "company_en": "Abnova  Corporation ", "category": "醫材製造/研發", "category_en": "Medical Device R&D, Manufacturing", "market": "上市", "market_en": "Listed", "EPS": -0.52, "growth": -0.31}, {"company": "國光生", "company_en": "Adimmune Corporation ", "category": "藥品製造/新藥研發", "category_en": "Bio-Pharmaceuticals", "market": "上市", "market_en": "Listed", "EPS": -2.2, "growth": -1.84}, {"company": "訊映", "company_en": "OK Biotech Co., Ltd. ", "category": "醫材製造/研發", "category_en": "Medical Device R&D, Manufacturing", "market": "上市", "market_en": "Listed", "EPS": -1.49, "growth": -20.2}, {"company": "承業醫", "company_en": "CHC Healthcare Group ", "category": "醫療通路/產品經銷", "category_en": "Pharmacy & Distributor", "market": "上市", "market_en": "Listed", "EPS": 0.3399999999999998, "growth": 4.93}, {"company": "泰博", "company_en": "TaiDoc Technology Corporation ", "category": "醫材製造/研發", "category_en": "Medical Device R&D, Manufacturing", "market": "上市", "market_en": "Listed", "EPS": 0.0, "growth": -3.79}, {"company": "華廣", "company_en": "Bionime Corporation ", "category": "醫材製造/研發", "category_en": "Medical Device R&D, Manufacturing", "market": "上市", "market_en": "Listed", "EPS": -1.4, "growth": -3.84}, {"company": "台耀", "company_en": "Formosa Laboratories, Inc. ", "category": "原料藥", "category_en": "APIs", "market": "上市", "market_en": "Listed", "EPS": -2.35, "growth": 1.31}, {"company": "藥華藥", "company_en": "PharmaEssentia Corporation ", "category": "藥品製造/新藥研發", "category_en": "Bio-Pharmaceuticals", "market": "上市", "market_en": "Listed", "EPS": 0.0, "growth": 1.2}, {"company": "保瑞", "company_en": "Bora Pharmaceuticals Co., LTD. ", "category": "藥品製造/新藥研發", "category_en": "Bio-Pharmaceuticals", "market": "上市", "market_en": "Listed", "EPS": 0.0, "growth": 5.79}, {"company": "晶碩", "company_en": "Pegavision Corporation ", "category": "醫材製造/研發", "category_en": "Medical Device R&D, Manufacturing", "market": "上市", "market_en": "Listed", "EPS": 0.7999999999999972, "growth": 9.21}, {"company": "正瀚-創", "company_en": "CH Biotech R&D Co., Ltd. ", "category": "農業生技/農科健康", "category_en": "Agriculture & Agricultural Science", "market": "上市", "market_en": "Listed", "EPS": 0.0, "growth": 0.0}, {"company": "金萬林-創", "company_en": "Kim Forest Enterprise Co., Ltd. ", "category": "生技服務/基因檢測服務", "category_en": "CRO Service & Genetic Testing", "market": "上市", "market_en": "Listed", "EPS": 0.0, "growth": 0.0}, {"company": "華安", "company_en": "Energenesis Biomedical CO.,LTD. ", "category": "藥品製造/新藥研發", "category_en": "Bio-Pharmaceuticals", "market": "上市", "market_en": "Listed", "EPS": 0.0, "growth": 0.0}, {"company": "視陽", "company_en": "Visco Vision Inc. ", "category": "醫材製造/研發", "category_en": "Medical Device R&D, Manufacturing", "market": "上市", "market_en": "Listed", "EPS": -6.319999999999999, "growth": -19.42}, {"company": "晉弘", "company_en": "Medimaging Integrated Solution Inc. ", "category": "醫材製造/研發", "category_en": "Medical Device R&D, Manufacturing", "market": "上市", "market_en": "Listed", "EPS": 0.0, "growth": 2.56}, {"company": "睿生光電", "company_en": "InnoCare Optoelectronics Corporation ", "category": "醫材製造/研發", "category_en": "Medical Device R&D, Manufacturing", "market": "上市", "market_en": "Listed", "EPS": 0.0, "growth": 0.0}, {"company": "精華", "company_en": "St.Shine Optical Co.,Ltd. ", "category": "醫材製造/研發", "category_en": "Medical Device R&D, Manufacturing", "market": "上櫃", "market_en": "OTC", "EPS": -9.38, "growth": -9.54}, {"company": "生泰", "company_en": "SYN-TECH Chem. & Pharm. Co., Ltd. ", "category": "原料藥", "category_en": "APIs", "market": "上櫃", "market_en": "OTC", "EPS": -0.9900000000000002, "growth": 2.26}, {"company": "合世", "company_en": "Health & Life Co., Ltd. ", "category": "醫材製造/研發", "category_en": "Medical Device R&D, Manufacturing", "market": "上櫃", "market_en": "OTC", "EPS": -0.3299999999999999, "growth": -1.8}, {"company": "訊聯", "company_en": "BIONET Corp. ", "category": "細胞療法/細胞儲存服務", "category_en": "Cell Therapy", "market": "上櫃", "market_en": "OTC", "EPS": 0.8699999999999999, "growth": 4.41}, {"company": "杏昌", "company_en": "Hi-Clearance Inc. ", "category": "醫療通路/產品經銷", "category_en": "Pharmacy & Distributor", "market": "上櫃", "market_en": "OTC", "EPS": -1.0500000000000007, "growth": 0.47}, {"company": "易威", "company_en": "Easywell Biomedicals, Inc. ", "category": "藥品製造/新藥研發", "category_en": "Bio-Pharmaceuticals", "market": "上櫃", "market_en": "OTC", "EPS": 0.1399999999999999, "growth": -6.36}, {"company": "寶利徠", "company_en": "Polylite Taiwan Co., Ltd. ", "category": "醫材製造/研發", "category_en": "Medical Device R&D, Manufacturing", "market": "上櫃", "market_en": "OTC", "EPS": 0.0999999999999999, "growth": 1.66}, {"company": "進階", "company_en": "Level Biotechnology Inc. ", "category": "生技服務/基因檢測服務", "category_en": "CRO Service & Genetic Testing", "market": "上櫃", "market_en": "OTC", "EPS": 0.1399999999999999, "growth": 12.05}, {"company": "基亞", "company_en": "Medigen Biotechnology Corp. ", "category": "藥品製造/新藥研發", "category_en": "Bio-Pharmaceuticals", "market": "上櫃", "market_en": "OTC", "EPS": 0.8300000000000001, "growth": -4.4}, {"company": "佰研", "company_en": "Sagittarius Life Science Corp ", "category": "食品生技及預防保健品", "category_en": "Food Science & Health Supplement", "market": "上櫃", "market_en": "OTC", "EPS": 0.5899999999999999, "growth": 4.33}, {"company": "大學光", "company_en": "Universal Vision Biotechnology Co., Ltd. ", "category": "醫療通路/產品經銷", "category_en": "Pharmacy & Distributor", "market": "上櫃", "market_en": "OTC", "EPS": 1.6999999999999993, "growth": 7.18}, {"company": "永日", "company_en": "Yung Zip Chemical Ind. Co., Ltd. ", "category": "原料藥", "category_en": "APIs", "market": "上櫃", "market_en": "OTC", "EPS": -0.1699999999999999, "growth": 11.23}, {"company": "東洋", "company_en": "TTY Biopharm Company Limited ", "category": "藥品製造/新藥研發", "category_en": "Bio-Pharmaceuticals", "market": "上櫃", "market_en": "OTC", "EPS": 0.1399999999999996, "growth": 3.15}, {"company": "邦特", "company_en": "Bioteque Corporation ", "category": "醫材製造/研發", "category_en": "Medical Device R&D, Manufacturing", "market": "上櫃", "market_en": "OTC", "EPS": -0.5899999999999999, "growth": -0.98}, {"company": "加捷生醫", "company_en": "Jia Jie Biomedical Co., Ltd. ", "category": "食品生技及預防保健品", "category_en": "Food Science & Health Supplement", "market": "上櫃", "market_en": "OTC", "EPS": 1.6800000000000002, "growth": 1.66}, {"company": "濟生", "company_en": "Chi Sheng Pharma & Biotech Co., Ltd ", "category": "藥品製造/新藥研發", "category_en": "Bio-Pharmaceuticals", "market": "上櫃", "market_en": "OTC", "EPS": -1.4900000000000002, "growth": 1.05}, {"company": "健喬", "company_en": "Synmosa Biopharma Corporation ", "category": "藥品製造/新藥研發", "category_en": "Bio-Pharmaceuticals", "market": "上櫃", "market_en": "OTC", "EPS": -0.8499999999999999, "growth": 4.76}, {"company": "明基醫", "company_en": "BenQ Medical Technology Corporation ", "category": "醫材製造/研發", "category_en": "Medical Device R&D, Manufacturing", "market": "上櫃", "market_en": "OTC", "EPS": -1.4700000000000002, "growth": -0.79}, {"company": "友華", "company_en": "Orient EuroPharma Co., Ltd. ", "category": "藥品製造/新藥研發", "category_en": "Bio-Pharmaceuticals", "market": "上櫃", "market_en": "OTC", "EPS": 5.24, "growth": -4.88}, {"company": "優盛", "company_en": "Rossmax International Ltd. ", "category": "醫材製造/研發", "category_en": "Medical Device R&D, Manufacturing", "market": "上櫃", "market_en": "OTC", "EPS": -2.09, "growth": -8.21}, {"company": "晟德", "company_en": "Center Laboratories, Inc. ", "category": "藥品製造/新藥研發", "category_en": "Bio-Pharmaceuticals", "market": "上櫃", "market_en": "OTC", "EPS": -1.67, "growth": 8.5}, {"company": "太醫", "company_en": "Pacific Hospital Supply Co., Ltd ", "category": "醫材製造/研發", "category_en": "Medical Device R&D, Manufacturing", "market": "上櫃", "market_en": "OTC", "EPS": 1.2400000000000002, "growth": -0.17}, {"company": "天良", "company_en": "Tien Liang BioTech Co., Ltd. ", "category": "食品生技及預防保健品", "category_en": "Food Science & Health Supplement", "market": "上櫃", "market_en": "OTC", "EPS": -0.91, "growth": -5.3}, {"company": "中天", "company_en": "Microbio Co., Ltd. ", "category": "食品生技及預防保健品", "category_en": "Food Science & Health Supplement", "market": "上櫃", "market_en": "OTC", "EPS": -2.52, "growth": -4.66}, {"company": "聯合", "company_en": "United Orthopedic Corporation ", "category": "醫材製造/研發", "category_en": "Medical Device R&D, Manufacturing", "market": "上櫃", "market_en": "OTC", "EPS": 1.66, "growth": 13.89}, {"company": "健亞", "company_en": "Genovate Biotechnology Co., Ltd. ", "category": "藥品製造/新藥研發", "category_en": "Bio-Pharmaceuticals", "market": "上櫃", "market_en": "OTC", "EPS": 0.38, "growth": 5.52}, {"company": "浩泰", "company_en": "DR.Chip Biotechnology Incorporation ", "category": "生技服務/基因檢測服務", "category_en": "CRO Service & Genetic Testing", "market": "上櫃", "market_en": "OTC", "EPS": -0.3800000000000001, "growth": 23.72}, {"company": "曜亞", "company_en": "Dynamic Medical Technologies Inc. ", "category": "醫學美容/藥妝保健", "category_en": "Aesthetic Medicine & Beauty Care", "market": "上櫃", "market_en": "OTC", "EPS": 1.7999999999999998, "growth": 3.75}, {"company": "中裕", "company_en": "TaiMed Biologics Inc. ", "category": "藥品製造/新藥研發", "category_en": "Bio-Pharmaceuticals", "market": "上櫃", "market_en": "OTC", "EPS": 0.3, "growth": 1.52}, {"company": "鈺緯", "company_en": "DIVA Laboratories, Ltd. ", "category": "醫材製造/研發", "category_en": "Medical Device R&D, Manufacturing", "market": "上櫃", "market_en": "OTC", "EPS": 0.4, "growth": 4.87}, {"company": "訊聯基因", "company_en": "Genetics Generation Advancement Corp. ", "category": "生技服務/基因檢測服務", "category_en": "CRO Service & Genetic Testing", "market": "上櫃", "market_en": "OTC", "EPS": 0.06, "growth": 1.25}, {"company": "聿新科", "company_en": "Bioptik Technology Incorporation ", "category": "醫材製造/研發", "category_en": "Medical Device R&D, Manufacturing", "market": "上櫃", "market_en": "OTC", "EPS": 0.6799999999999999, "growth": 2.37}, {"company": "智擎", "company_en": "PharmaEngine, Inc. ", "category": "藥品製造/新藥研發", "category_en": "Bio-Pharmaceuticals", "market": "上櫃", "market_en": "OTC", "EPS": -0.3100000000000003, "growth": -17.71}, {"company": "鐿鈦", "company_en": "INTAI Technology Corporation ", "category": "醫材製造/研發", "category_en": "Medical Device R&D, Manufacturing", "market": "上櫃", "market_en": "OTC", "EPS": -1.7000000000000002, "growth": -2.48}, {"company": "松瑞藥", "company_en": "Savior Lifetec Corporation ", "category": "原料藥", "category_en": "APIs", "market": "上櫃", "market_en": "OTC", "EPS": -0.02, "growth": 4.78}, {"company": "醣聯", "company_en": "GlycoNex Incorporation ", "category": "藥品製造/新藥研發", "category_en": "Bio-Pharmaceuticals", "market": "上櫃", "market_en": "OTC", "EPS": 0.56, "growth": 8.29}, {"company": "久裕", "company_en": "Arich Enterprise Co., Ltd. ", "category": "醫療通路/產品經銷", "category_en": "Pharmacy & Distributor", "market": "上櫃", "market_en": "OTC", "EPS": 0.19, "growth": 7.89}, {"company": "浩鼎", "company_en": "OBI Pharma, Inc. ", "category": "藥品製造/新藥研發", "category_en": "Bio-Pharmaceuticals", "market": "上櫃", "market_en": "OTC", "EPS": 2.6999999999999997, "growth": 4.43}, {"company": "杏一", "company_en": "MedFirst Healthcare Services, Inc. ", "category": "醫療通路/產品經銷", "category_en": "Pharmacy & Distributor", "market": "上櫃", "market_en": "OTC", "EPS": -3.7, "growth": 5.91}, {"company": "福永生技", "company_en": "EPS Bio Technology Corp. ", "category": "醫材製造/研發", "category_en": "Medical Device R&D, Manufacturing", "market": "上櫃", "market_en": "OTC", "EPS": -0.19, "growth": 3.51}, {"company": "安克", "company_en": "AmCad BioMed Corporation ", "category": "醫材製造/研發", "category_en": "Medical Device R&D, Manufacturing", "market": "上櫃", "market_en": "OTC", "EPS": 0.16, "growth": 0.35}, {"company": "杏國", "company_en": "SynCore Biotechnology Co.,Ltd ", "category": "藥品製造/新藥研發", "category_en": "Bio-Pharmaceuticals", "market": "上櫃", "market_en": "OTC", "EPS": 0.4499999999999999, "growth": 1.56}, {"company": "欣大健康", "company_en": "S&S Healthcare Holding Ltd. ", "category": "醫材製造/研發", "category_en": "Medical Device R&D, Manufacturing", "market": "上櫃", "market_en": "OTC", "EPS": 8.26, "growth": -3.48}, {"company": "永昕", "company_en": "Mycenax Biotech Inc. ", "category": "藥品製造/新藥研發", "category_en": "Bio-Pharmaceuticals", "market": "上櫃", "market_en": "OTC", "EPS": -0.5799999999999996, "growth": 5.65}, {"company": "雙美", "company_en": "Sunmax Biotechnology Co., Ltd. ", "category": "醫材製造/研發", "category_en": "Medical Device R&D, Manufacturing", "market": "上櫃", "market_en": "OTC", "EPS": 1.6899999999999995, "growth": 1.94}, {"company": "豪展", "company_en": "AViTA Corporation ", "category": "醫材製造/研發", "category_en": "Medical Device R&D, Manufacturing", "market": "上櫃", "market_en": "OTC", "EPS": -1.58, "growth": 9.14}, {"company": "合一", "company_en": "Oneness Biotech Co., Ltd. ", "category": "藥品製造/新藥研發", "category_en": "Bio-Pharmaceuticals", "market": "上櫃", "market_en": "OTC", "EPS": -3.84, "growth": -1.72}, {"company": "皇將", "company_en": "CVC Technologies Inc. ", "category": "醫材製造/研發", "category_en": "Medical Device R&D, Manufacturing", "market": "上櫃", "market_en": "OTC", "EPS": -0.97, "growth": 3.87}, {"company": "強生製藥", "company_en": "Johnson Chemical Pharmaceutical Works Co., Ltd. ", "category": "藥品製造/新藥研發", "category_en": "Bio-Pharmaceuticals", "market": "上櫃", "market_en": "OTC", "EPS": 0.08, "growth": 18.44}, {"company": "德英", "company_en": "G&E Herbal Biotechnology Co., Ltd. ", "category": "藥品製造/新藥研發", "category_en": "Bio-Pharmaceuticals", "market": "上櫃", "market_en": "OTC", "EPS": 1.17, "growth": 10.14}, {"company": "寶島科", "company_en": "Formosa Optical Technology Co.,Ltd. ", "category": "醫療通路/產品經銷", "category_en": "Pharmacy & Distributor", "market": "上櫃", "market_en": "OTC", "EPS": 4.13, "growth": 8.84}, {"company": "上亞科技", "company_en": "Singbao International Co. Ltd ", "category": "醫學美容/藥妝保健", "category_en": "Aesthetic Medicine & Beauty Care", "market": "上櫃", "market_en": "OTC", "EPS": -1.84, "growth": 3.38}, {"company": "立康", "company_en": "Li Kang Biomedical Co., Ltd. ", "category": "食品生技及預防保健品", "category_en": "Food Science & Health Supplement", "market": "上櫃", "market_en": "OTC", "EPS": -0.6699999999999999, "growth": 2.38}, {"company": "益得", "company_en": "Intech Biopharm Corporation ", "category": "藥品製造/新藥研發", "category_en": "Bio-Pharmaceuticals", "market": "上櫃", "market_en": "OTC", "EPS": 0.0099999999999997, "growth": 4.91}, {"company": "大樹", "company_en": "Great Tree Pharmacy Co., Ltd. ", "category": "醫療通路/產品經銷", "category_en": "Pharmacy & Distributor", "market": "上櫃", "market_en": "OTC", "EPS": -1.85, "growth": -0.92}, {"company": "生華科", "company_en": "Senhwa Biosciences, Inc. ", "category": "藥品製造/新藥研發", "category_en": "Bio-Pharmaceuticals", "market": "上櫃", "market_en": "OTC", "EPS": 0.6000000000000001, "growth": -6.52}, {"company": "科懋", "company_en": "Excelsior Biopharma Inc. ", "category": "藥品製造/新藥研發", "category_en": "Bio-Pharmaceuticals", "market": "上櫃", "market_en": "OTC", "EPS": -1.24, "growth": -0.49}, {"company": "益安", "company_en": "Medeon Biodesign, Inc. ", "category": "醫材製造/研發", "category_en": "Medical Device R&D, Manufacturing", "market": "上櫃", "market_en": "OTC", "EPS": -8.14, "growth": -0.2}, {"company": "達爾膚", "company_en": "Dr. Wu Skincare Co., Ltd. ", "category": "醫學美容/藥妝保健", "category_en": "Aesthetic Medicine & Beauty Care", "market": "上櫃", "market_en": "OTC", "EPS": 1.88, "growth": 37.06}, {"company": "明達醫", "company_en": "Crystalvue Medical Corporation ", "category": "醫材製造/研發", "category_en": "Medical Device R&D, Manufacturing", "market": "上櫃", "market_en": "OTC", "EPS": -0.6900000000000004, "growth": -15.49}, {"company": "順藥", "company_en": "Lumosa Therapeutics Co., Ltd. ", "category": "藥品製造/新藥研發", "category_en": "Bio-Pharmaceuticals", "market": "上櫃", "market_en": "OTC", "EPS": 1.5799999999999998, "growth": 2.24}, {"company": "高端疫苗", "company_en": "Medigen Vaccine Biologics Corporation ", "category": "藥品製造/新藥研發", "category_en": "Bio-Pharmaceuticals", "market": "上櫃", "market_en": "OTC", "EPS": 1.0299999999999998, "growth": -21.78}, {"company": "醫揚", "company_en": "Onyx Healthcare Inc. ", "category": "醫材製造/研發", "category_en": "Medical Device R&D, Manufacturing", "market": "上櫃", "market_en": "OTC", "EPS": 1.41, "growth": 2.73}, {"company": "霈方", "company_en": "Mikobeaute International Co., Ltd. ", "category": "醫學美容/藥妝保健", "category_en": "Aesthetic Medicine & Beauty Care", "market": "上櫃", "market_en": "OTC", "EPS": -0.9699999999999998, "growth": 25.43}, {"company": "逸達", "company_en": "Foresee Pharmaceuticals Co., Ltd. ", "category": "藥品製造/新藥研發", "category_en": "Bio-Pharmaceuticals", "market": "上櫃", "market_en": "OTC", "EPS": -4.140000000000001, "growth": 10.02}, {"company": "台康生技", "company_en": "EirGenix Inc. ", "category": "藥品製造/新藥研發", "category_en": "Bio-Pharmaceuticals", "market": "上櫃", "market_en": "OTC", "EPS": -2.62, "growth": 5.43}, {"company": "奈米醫材", "company_en": "ICARES Medicus, Inc. ", "category": "醫材製造/研發", "category_en": "Medical Device R&D, Manufacturing", "market": "上櫃", "market_en": "OTC", "EPS": -1.0, "growth": 2.68}, {"company": "慧智", "company_en": "Sofiva Genomics Co.,Ltd. ", "category": "生技服務/基因檢測服務", "category_en": "CRO Service & Genetic Testing", "market": "上櫃", "market_en": "OTC", "EPS": -1.46, "growth": -0.88}, {"company": "台生材", "company_en": "Taiwan Biomaterial Co., Ltd. ", "category": "醫材製造/研發", "category_en": "Medical Device R&D, Manufacturing", "market": "上櫃", "market_en": "OTC", "EPS": -1.0699999999999998, "growth": -2.69}, {"company": "威健生技", "company_en": "Welgene Biotech Co.,Ltd. ", "category": "生技服務/基因檢測服務", "category_en": "CRO Service & Genetic Testing", "market": "上櫃", "market_en": "OTC", "EPS": -0.52, "growth": 1.33}, {"company": "樂斯科", "company_en": "BioLASCO Taiwan Co., Ltd. ", "category": "生技服務/基因檢測服務", "category_en": "CRO Service & Genetic Testing", "market": "上櫃", "market_en": "OTC", "EPS": 0.29, "growth": -3.17}, {"company": "軒郁", "company_en": "Shiny Brands Group Co., Ltd. ", "category": "醫學美容/藥妝保健", "category_en": "Aesthetic Medicine & Beauty Care", "market": "上櫃", "market_en": "OTC", "EPS": 6.87, "growth": 31.72}, {"company": "長聖", "company_en": "Ever Supreme Bio Technology Co., Ltd ", "category": "細胞療法/細胞儲存服務", "category_en": "Cell Therapy", "market": "上櫃", "market_en": "OTC", "EPS": 4.29, "growth": 5.1}, {"company": "博晟生醫", "company_en": "BioGend Therapeutics Co., Ltd. ", "category": "醫材製造/研發", "category_en": "Medical Device R&D, Manufacturing", "market": "上櫃", "market_en": "OTC", "EPS": 0.49, "growth": 27.7}, {"company": "亨泰光", "company_en": "Brighten Optix Corporation ", "category": "醫材製造/研發", "category_en": "Medical Device R&D, Manufacturing", "market": "上櫃", "market_en": "OTC", "EPS": -2.3200000000000003, "growth": -3.6}, {"company": "達亞", "company_en": "Delta Asia International Corporation ", "category": "醫材製造/研發", "category_en": "Medical Device R&D, Manufacturing", "market": "上櫃", "market_en": "OTC", "EPS": -3.31, "growth": 3.74}, {"company": "台微醫", "company_en": "Wiltrom Co., Ltd. ", "category": "醫材製造/研發", "category_en": "Medical Device R&D, Manufacturing", "market": "上櫃", "market_en": "OTC", "EPS": 0.63, "growth": -3.2}, {"company": "昱展新藥", "company_en": "Alar Pharmaceuticals Inc. ", "category": "藥品製造/新藥研發", "category_en": "Bio-Pharmaceuticals", "market": "上櫃", "market_en": "OTC", "EPS": 0.0, "growth": 0.0}, {"company": "長佳智能", "company_en": "Ever Fortune.AI Co., Ltd. ", "category": "醫材製造/研發", "category_en": "Medical Device R&D, Manufacturing", "market": "上櫃", "market_en": "OTC", "EPS": 0.0, "growth": 0.0}, {"company": "國邑*", "company_en": "Pharmosa Biopharm Inc. ", "category": "藥品製造/新藥研發", "category_en": "Bio-Pharmaceuticals", "market": "上櫃", "market_en": "OTC", "EPS": 0.0, "growth": 0.0}, {"company": "佑全", "company_en": "WE CAN MEDICINES CO LTD ", "category": "醫療通路/產品經銷", "category_en": "Pharmacy & Distributor", "market": "上櫃", "market_en": "OTC", "EPS": 0.0, "growth": 0.0}, {"company": "生展", "company_en": "Syngen Biotech Co.,Ltd. ", "category": "食品生技及預防保健品", "category_en": "Food Science & Health Supplement", "market": "上櫃", "market_en": "OTC", "EPS": -1.709999999999999, "growth": -5.64}, {"company": "盛弘", "company_en": "ShareHope Medicine Co., Ltd. ", "category": "醫療通路/產品經銷", "category_en": "Pharmacy & Distributor", "market": "上櫃", "market_en": "OTC", "EPS": -1.4600000000000002, "growth": -6.97}, {"company": "商之器", "company_en": "EBM Technologies Incorporated ", "category": "醫材製造/研發", "category_en": "Medical Device R&D, Manufacturing", "market": "上櫃", "market_en": "OTC", "EPS": -0.5700000000000001, "growth": 0.57}, {"company": "東生華", "company_en": "TSH Biopharm Corporation Limited ", "category": "藥品製造/新藥研發", "category_en": "Bio-Pharmaceuticals", "market": "上櫃", "market_en": "OTC", "EPS": 0.0, "growth": -3.15}, {"company": "大江", "company_en": "TCI Co., Ltd. ", "category": "食品生技及預防保健品", "category_en": "Food Science & Health Supplement", "market": "上櫃", "market_en": "OTC", "EPS": 1.6700000000000008, "growth": -10.81}]}